ezpysocket/__init__.py
ezpysocket/ezpysocket.py
ezpysocket-0.0.3.dist-info/LICENSE
ezpysocket-0.0.3.dist-info/METADATA
ezpysocket-0.0.3.dist-info/WHEEL
ezpysocket-0.0.3.dist-info/top_level.txt
ezpysocket-0.0.3.dist-info/RECORD
