Metadata-Version: 2.1
Name: ezpysocket
Version: 0.0.3
Summary: Cpp Python socket abstraction library that attempts to simplify TCP/IP socket communication.
Home-page: https://github.com/Aditya-Diva/Ez-Cpp-Python-Socket
Author: Aditya Divakaran
Author-email: adi.develops@gmail.com
License: UNKNOWN
Platform: UNKNOWN
Classifier: Programming Language :: Python :: 3
Classifier: License :: OSI Approved :: MIT License
Classifier: Operating System :: OS Independent
Requires-Python: >=3.6
Requires-Dist: numpy
